{
    "codeToName": {
        "13": "CR",
        "32": "space",
        "33": "exclam",
        "34": "quotedbl",
        "35": "numbersign",
        "36": "dollar",
        "37": "percent",
        "38": "ampersand",
        "39": "quotesingle",
        "40": "parenleft",
        "41": "parenright",
        "42": "asterisk",
        "43": "plus",
        "44": "comma",
        "45": "hyphen",
        "46": "period",
        "47": "slash",
        "48": "zero",
        "49": "one",
        "50": "two",
        "51": "three",
        "52": "four",
        "53": "five",
        "54": "six",
        "55": "seven",
        "56": "eight",
        "57": "nine",
        "58": "colon",
        "59": "semicolon",
        "60": "less",
        "61": "equal",
        "62": "greater",
        "63": "question",
        "64": "at",
        "65": "A",
        "66": "B",
        "67": "C",
        "68": "D",
        "69": "E",
        "70": "F",
        "71": "G",
        "72": "H",
        "73": "I",
        "74": "J",
        "75": "K",
        "76": "L",
        "77": "M",
        "78": "N",
        "79": "O",
        "80": "P",
        "81": "Q",
        "82": "R",
        "83": "S",
        "84": "T",
        "85": "U",
        "86": "V",
        "87": "W",
        "88": "X",
        "89": "Y",
        "90": "Z",
        "91": "bracketleft",
        "92": "backslash",
        "93": "bracketright",
        "94": "asciicircum",
        "95": "underscore",
        "96": "grave",
        "97": "a",
        "98": "b",
        "99": "c",
        "100": "d",
        "101": "e",
        "102": "f",
        "103": "g",
        "104": "h",
        "105": "i",
        "106": "j",
        "107": "k",
        "108": "l",
        "109": "m",
        "110": "n",
        "111": "o",
        "112": "p",
        "113": "q",
        "114": "r",
        "115": "s",
        "116": "t",
        "117": "u",
        "118": "v",
        "119": "w",
        "120": "x",
        "121": "y",
        "122": "z",
        "123": "braceleft",
        "124": "bar",
        "125": "braceright",
        "126": "asciitilde",
        "160": "uni00A0",
        "161": "exclamdown",
        "162": "cent",
        "163": "sterling",
        "164": "currency",
        "165": "yen",
        "166": "brokenbar",
        "167": "section",
        "168": "dieresis",
        "169": "copyright",
        "170": "ordfeminine",
        "171": "guillemotleft",
        "172": "logicalnot",
        "173": "uni00AD",
        "174": "registered",
        "175": "macron",
        "176": "degree",
        "177": "plusminus",
        "178": "uni00B2",
        "179": "uni00B3",
        "180": "acute",
        "181": "uni00B5",
        "182": "paragraph",
        "183": "periodcentered",
        "184": "cedilla",
        "185": "uni00B9",
        "186": "ordmasculine",
        "187": "guillemotright",
        "188": "onequarter",
        "189": "onehalf",
        "190": "threequarters",
        "191": "questiondown",
        "192": "Agrave",
        "193": "Aacute",
        "194": "Acircumflex",
        "195": "Atilde",
        "196": "Adieresis",
        "197": "Aring",
        "198": "AE",
        "199": "Ccedilla",
        "200": "Egrave",
        "201": "Eacute",
        "202": "Ecircumflex",
        "203": "Edieresis",
        "204": "Igrave",
        "205": "Iacute",
        "206": "Icircumflex",
        "207": "Idieresis",
        "208": "Eth",
        "209": "Ntilde",
        "210": "Ograve",
        "211": "Oacute",
        "212": "Ocircumflex",
        "213": "Otilde",
        "214": "Odieresis",
        "215": "multiply",
        "216": "Oslash",
        "217": "Ugrave",
        "218": "Uacute",
        "219": "Ucircumflex",
        "220": "Udieresis",
        "221": "Yacute",
        "222": "Thorn",
        "223": "germandbls",
        "224": "agrave",
        "225": "aacute",
        "226": "acircumflex",
        "227": "atilde",
        "228": "adieresis",
        "229": "aring",
        "230": "ae",
        "231": "ccedilla",
        "232": "egrave",
        "233": "eacute",
        "234": "ecircumflex",
        "235": "edieresis",
        "236": "igrave",
        "237": "iacute",
        "238": "icircumflex",
        "239": "idieresis",
        "240": "eth",
        "241": "ntilde",
        "242": "ograve",
        "243": "oacute",
        "244": "ocircumflex",
        "245": "otilde",
        "246": "odieresis",
        "247": "divide",
        "248": "oslash",
        "249": "ugrave",
        "250": "uacute",
        "251": "ucircumflex",
        "252": "udieresis",
        "253": "yacute",
        "254": "thorn",
        "255": "ydieresis",
        "258": "Abreve",
        "305": "dotlessi",
        "338": "OE",
        "339": "oe",
        "700": "uni02BC",
        "710": "circumflex",
        "730": "ring",
        "732": "tilde",
        "768": "gravecomb",
        "769": "acutecomb",
        "771": "tildecomb",
        "772": "uni0304",
        "776": "uni0308",
        "777": "hookabovecomb",
        "803": "dotbelowcomb",
        "8201": "uni2009",
        "8211": "endash",
        "8212": "emdash",
        "8216": "quoteleft",
        "8217": "quoteright",
        "8218": "quotesinglbase",
        "8220": "quotedblleft",
        "8221": "quotedblright",
        "8222": "quotedblbase",
        "8226": "bullet",
        "8230": "ellipsis",
        "8242": "minute",
        "8243": "second",
        "8249": "guilsinglleft",
        "8250": "guilsinglright",
        "8260": "fraction",
        "8308": "uni2074",
        "8364": "Euro",
        "8482": "trademark",
        "8593": "arrowup",
        "8595": "arrowdown",
        "8722": "minus",
        "8725": "uni2215",
        "65279": "uniFEFF"
    },
    "isUnicode": true,
    "EncodingScheme": "FontSpecific",
    "FontName": "Archivo SemiBold",
    "FullName": "Archivo SemiBold Bold",
    "Version": "Version 2.001",
    "PostScriptName": "ArchivoSemiBold-Bold",
    "Weight": "Bold",
    "ItalicAngle": "0",
    "IsFixedPitch": "false",
    "UnderlineThickness": "44",
    "UnderlinePosition": "-148",
    "FontHeightOffset": "0",
    "Ascender": "878",
    "Descender": "-210",
    "FontBBox": [
        "-236",
        "-208",
        "1149",
        "1047"
    ],
    "StartCharMetrics": "303",
    "C": {
        "13": 600,
        "32": 196,
        "33": 301,
        "34": 456,
        "35": 600,
        "36": 556,
        "37": 973,
        "38": 764,
        "39": 253,
        "40": 364,
        "41": 364,
        "42": 407,
        "43": 641,
        "44": 307,
        "45": 333,
        "46": 307,
        "47": 300,
        "48": 595,
        "49": 596,
        "50": 596,
        "51": 596,
        "52": 597,
        "53": 595,
        "54": 596,
        "55": 596,
        "56": 596,
        "57": 595,
        "58": 335,
        "59": 335,
        "60": 641,
        "61": 641,
        "62": 641,
        "63": 613,
        "64": 1001,
        "65": 724,
        "66": 722,
        "67": 733,
        "68": 739,
        "69": 683,
        "70": 622,
        "71": 802,
        "72": 754,
        "73": 301,
        "74": 603,
        "75": 725,
        "76": 591,
        "77": 872,
        "78": 754,
        "79": 793,
        "80": 681,
        "81": 793,
        "82": 730,
        "83": 679,
        "84": 641,
        "85": 748,
        "86": 694,
        "87": 964,
        "88": 706,
        "89": 699,
        "90": 653,
        "91": 350,
        "92": 300,
        "93": 350,
        "94": 641,
        "95": 518,
        "96": 228,
        "97": 580,
        "98": 608,
        "99": 573,
        "100": 608,
        "101": 584,
        "102": 325,
        "103": 607,
        "104": 602,
        "105": 267,
        "106": 264,
        "107": 570,
        "108": 267,
        "109": 891,
        "110": 602,
        "111": 613,
        "112": 608,
        "113": 608,
        "114": 380,
        "115": 556,
        "116": 342,
        "117": 601,
        "118": 547,
        "119": 798,
        "120": 572,
        "121": 547,
        "122": 519,
        "123": 393,
        "124": 253,
        "125": 393,
        "126": 641,
        "160": 196,
        "161": 301,
        "162": 597,
        "163": 599,
        "164": 597,
        "165": 595,
        "166": 253,
        "167": 598,
        "168": 326,
        "169": 772,
        "170": 398,
        "171": 576,
        "172": 641,
        "173": 333,
        "174": 772,
        "175": 307,
        "176": 400,
        "177": 641,
        "178": 371,
        "179": 371,
        "180": 228,
        "181": 605,
        "182": 616,
        "183": 333,
        "184": 237,
        "185": 371,
        "186": 393,
        "187": 576,
        "188": 887,
        "189": 887,
        "190": 887,
        "191": 613,
        "192": 724,
        "193": 724,
        "194": 724,
        "195": 724,
        "196": 724,
        "197": 724,
        "198": 1004,
        "199": 733,
        "200": 683,
        "201": 683,
        "202": 683,
        "203": 683,
        "204": 301,
        "205": 301,
        "206": 301,
        "207": 301,
        "208": 739,
        "209": 754,
        "210": 793,
        "211": 793,
        "212": 793,
        "213": 793,
        "214": 793,
        "215": 641,
        "216": 793,
        "217": 748,
        "218": 748,
        "219": 748,
        "220": 748,
        "221": 699,
        "222": 697,
        "223": 634,
        "224": 580,
        "225": 580,
        "226": 580,
        "227": 580,
        "228": 580,
        "229": 580,
        "230": 920,
        "231": 573,
        "232": 584,
        "233": 584,
        "234": 584,
        "235": 584,
        "236": 267,
        "237": 267,
        "238": 267,
        "239": 267,
        "240": 626,
        "241": 602,
        "242": 613,
        "243": 613,
        "244": 613,
        "245": 613,
        "246": 613,
        "247": 641,
        "248": 613,
        "249": 601,
        "250": 601,
        "251": 601,
        "252": 601,
        "253": 547,
        "254": 608,
        "255": 547,
        "258": 724,
        "305": 267,
        "338": 1202,
        "339": 965,
        "700": 133,
        "710": 349,
        "730": 204,
        "732": 357,
        "768": 0,
        "769": 0,
        "771": 0,
        "772": 0,
        "776": 0,
        "777": 0,
        "803": 0,
        "8201": 211,
        "8211": 500,
        "8212": 1000,
        "8216": 280,
        "8217": 280,
        "8218": 280,
        "8220": 488,
        "8221": 488,
        "8222": 488,
        "8226": 441,
        "8230": 973,
        "8242": 168,
        "8243": 342,
        "8249": 357,
        "8250": 357,
        "8260": 167,
        "8308": 371,
        "8364": 599,
        "8482": 1001,
        "8593": 500,
        "8595": 500,
        "8722": 641,
        "8725": 132,
        "65279": 0
    },
    "CIDtoGID_Compressed": true,
    "CIDtoGID": "eJzt21Wv4FQYhtGnuA8zuLu7ywXu7gSCu7tzjes\/wd0twd3d3d1hQuaCkDMEGTgkrJXsvduv7dd39741Ua9O\/NKvvNSNvdAdvdlXfdeL3d093d57XduDXdOdndXZndO5ndf5XdCFXdTFXdf1fdJHfdzNfdvQdE3fjI1p1mZr9uZo3uZr\/hZowRZu6ZZtuZZvhVZstVZvjdZs7e7vrh7oix4dZmmdNmnTNm\/Ltmv7dmjHdm+P9myv9m7fDu3wjujIju6YTuykTu6UTu\/eYYru67M\/tMPf93I39Xpv90bvDFP2wzCuHzujZ\/q8h\/ppmHMY+rRLu2yYtS\/7vluHubqkM3u2q7qyq7ulqZqsKZqmKZu6aZuhWZq5sY1rnuZsruZuphZq8RZp0ZZssT5oiVZtpVZuldZqmY5qg9ZtvTZq\/TZs4zZr27Zq67Zpt3Zul3Zti\/bpwPZr\/w7ugD7soE7o2I7r+E7tsE77ZQ+TT4LvMHE7\/e0OS3XIJMgB\/xnDVCPUZvuDz84+fswxiXJMP8wwfp5xGDPhfOph5r\/QZeykSQMAAAAAAAAAAAAAAAAAwAheGaH2cI9MOHqqp3ts\/PpET\/b4hNptE9YbRm44TDb8+g\/z53p+hJuu+AtJ\/4zL\/+H+v\/XWv\/y+UTSMdoB\/1tfjxzejHWJUvf\/L\/O4opwAAAAAAAAAAAAAAAAAAAAAAAAAAAAAAAAAAAAAAAAAAAAAAAAAAAAAAAAAAAAAAAAAAAAAAAAAAAAAAAAAAAAAAAAAAAAAAAAAAAAAAAAAAAAAAAAAAAAAAAAAAAAAAAAAAAAAAAAAAAAAAAADg\/+O10Q7A6PoZWDZmjg==",
    "_version_": 6
}